metalmaps/__init__.py
metalmaps/__version__.py
metalmaps/colorcycle.py
metalmaps/colors.py
metalmaps/make_cmap.py
metalmaps-2.1.0.dist-info/LICENSE.txt
metalmaps-2.1.0.dist-info/METADATA
metalmaps-2.1.0.dist-info/WHEEL
metalmaps-2.1.0.dist-info/top_level.txt
metalmaps-2.1.0.dist-info/RECORD
