Metadata-Version: 2.1
Name: metalmaps
Version: 2.1.0
Summary: Metal and rock inspired Matplotlib colormaps.
Author-email: Mladen Ivkovic <mladen.ivkovic@hotmail.com>
License: GNU LESSER GENERAL PUBLIC LICENSE
Project-URL: Homepage, https://github.com/mladenivkovic/metalmaps
Project-URL: Gallery, https://mladenivkovic.github.io/metalmaps/metalmaps.html
Keywords: metal,rock,colormap,matplotlib
Classifier: Programming Language :: Python
Classifier: Programming Language :: Python :: 3
Classifier: License :: OSI Approved :: GNU Lesser General Public License v3 or later (LGPLv3+)
Classifier: Operating System :: OS Independent
License-File: LICENSE.txt
Requires-Dist: matplotlib
Requires-Dist: cycler
